[
	{
		"name": "City in the Sky",
		"children": [
			{
				"name": "3F",
				"children": [
					{
						"map_locations": [
							{
								"map": "cs3f",
								"x": 52,
								"y": 417
							},
							{
								"map": "csfull",
								"x": 4528,
								"y": 2172
							}
						],
						"sections": [
							{
								"name": "Baba Tower Top Small Chest",
								"access_rules": [
									"@CityinTheSkyWestWing, $canDefeatBabaSerpent, doubleclawshot, $canDefeatBigBaba",
									"@CityinTheSkyWestWing, $canDefeatBabaSerpentGlitched, doubleclawshot, $canDefeatBigBaba",
									"@CityinTheSkyWestWing, $canDefeatBabaSerpent, doubleclawshot, $canDefeatBigBabaGlitched",
									"@CityinTheSkyWestWing, $canDefeatBabaSerpentGlitched, doubleclawshot, $canDefeatBigBabaGlitched"
								]
							}
						]
					},
					{
						"map_locations": [
							{
								"map": "cs3f",
								"x": 48,
								"y": 721
							},
							{
								"map": "csfull",
								"x": 4524,
								"y": 2476
							}
						],
						"sections": [
							{
								"name": "West Garden Corner Chest",
								"access_rules": [
									"@CityinTheSkyWestWing, doubleclawshot"
								]
							}
						]
					},
					{
						"map_locations": [
							{
								"map": "cs3f",
								"x": 271,
								"y": 785
							},
							{
								"map": "csfull",
								"x": 4747,
								"y": 2540
							}
						],
						"sections": [
							{
								"name": "West Garden Ledge Chest",
								"access_rules": [
									"@CityinTheSkyWestWing, doubleclawshot"
								]
							}
						]
					},
					{
						"map_locations": [
							{
								"map": "cs3f",
								"x": 910,
								"y": 631
							},
							{
								"map": "csfull",
								"x": 5386,
								"y": 2386
							}
						],
						"sections": [
							{
								"name": "Chest Below Big Key Chest",
								"access_rules": [
									"@CityinTheSkyCentrakTowerSecondFloor, $canDefeatHelmasaur",
									"[glitcheson], @CityinTheSkyCentrakTowerSecondFloor, $canDefeatHelmasaurGlitched"
								]
							}
						]
					}
				]
			}
		]
	}
]